monox/__init__.py
monox/errors.py
monox/monox.py
monox-0.0.1.dist-info/METADATA
monox-0.0.1.dist-info/WHEEL
monox-0.0.1.dist-info/top_level.txt
monox-0.0.1.dist-info/RECORD
