Metadata-Version: 2.1
Name: monox
Version: 0.0.1
Summary: Monobank API Wrapper
Home-page: UNKNOWN
Author: Arwichok
Author-email: arwichok@gmail.com
License: MIT
Platform: UNKNOWN
Requires-Dist: pydantic (~=1.8.2)
Requires-Dist: pytest (~=6.2.4)
Requires-Dist: httpx (~=0.18.2)
Requires-Dist: respx (~=0.17.1)
